langnativ/__init__.py
langnativ/__main__.py
langnativ-0.1.0.dist-info/licenses/LICENSE
langnativ-0.1.0.dist-info/METADATA
langnativ-0.1.0.dist-info/WHEEL
langnativ-0.1.0.dist-info/top_level.txt
langnativ-0.1.0.dist-info/RECORD
