Metadata-Version: 2.4
Name: langnativ
Version: 0.1.0
Summary: langnativ
Author-email: KerstenBreuer <kersten-breuer@outlook.com>
License: Apache 2.0
Project-URL: Repository, https://github.com/kerstenbreuer/langnativ
Classifier: Development Status :: 1 - Planning
Classifier: Operating System :: POSIX :: Linux
Classifier: Programming Language :: Python :: 3.9
Classifier: Programming Language :: Python :: 3.10
Classifier: Programming Language :: Python :: 3.11
Classifier: License :: OSI Approved :: Apache Software License
Classifier: Topic :: Internet :: WWW/HTTP :: HTTP Servers
Classifier: Topic :: Software Development :: Libraries
Classifier: Intended Audience :: Developers
Requires-Python: >=3.9
License-File: LICENSE
Requires-Dist: pydantic>=2.5.3
Dynamic: license-file
